<?xml version="1.0" encoding="big5"?>
<F05DOC>
  <DOCHEAD>
    <DOCDATE>20171112</DOCDATE>
    <FROMPARTNERCODE>CVS</FROMPARTNERCODE>
    <TOPARTNERCODE>248</TOPARTNERCODE>
  </DOCHEAD>
  <F05CONTENT>
    <BC1>248010990</BC1>
    <BC2>0000631930000083</BC2>
    <STNO>F009227</STNO>
    <RTDT>20171111</RTDT>
    <TKDT>20171112</TKDT>
  </F05CONTENT>
  <F05CONTENT>
    <BC1>248010990</BC1>
    <BC2>0000639030000055</BC2>
    <STNO>F004208</STNO>
    <RTDT>20171111</RTDT>
    <TKDT>20171112</TKDT>
  </F05CONTENT>
  <F05CONTENT>
    <BC1>248010990</BC1>
    <BC2>0000639130000056</BC2>
    <STNO>F013293</STNO>
    <RTDT>20171111</RTDT>
    <TKDT>20171112</TKDT>
  </F05CONTENT>
</F05DOC>