<?xml version="1.0" encoding="big5"?>
<F05DOC>
  <DOCHEAD>
    <DOCDATE>20171111</DOCDATE>
    <FROMPARTNERCODE>CVS</FROMPARTNERCODE>
    <TOPARTNERCODE>248</TOPARTNERCODE>
  </DOCHEAD>
  <F05CONTENT>
    <BC1>248010990</BC1>
    <BC2>0000623830000011</BC2>
    <STNO>F013421</STNO>
    <RTDT>20171110</RTDT>
    <TKDT>20171111</TKDT>
  </F05CONTENT>
  <F05CONTENT>
    <BC1>248010990</BC1>
    <BC2>0000625130000015</BC2>
    <STNO>F004540</STNO>
    <RTDT>20171110</RTDT>
    <TKDT>20171111</TKDT>
  </F05CONTENT>
  <F05CONTENT>
    <BC1>248010990</BC1>
    <BC2>0000626830000021</BC2>
    <STNO>F010939</STNO>
    <RTDT>20171109</RTDT>
    <TKDT>20171111</TKDT>
  </F05CONTENT>
  <F05CONTENT>
    <BC1>248010990</BC1>
    <BC2>0000627530000039</BC2>
    <STNO>K001248</STNO>
    <RTDT>20171110</RTDT>
    <TKDT>20171111</TKDT>
  </F05CONTENT>
  <F05CONTENT>
    <BC1>248010990</BC1>
    <BC2>0000629730000058</BC2>
    <STNO>F009178</STNO>
    <RTDT>20171110</RTDT>
    <TKDT>20171111</TKDT>
  </F05CONTENT>
  <F05CONTENT>
    <BC1>248010990</BC1>
    <BC2>0000630930000073</BC2>
    <STNO>F015336</STNO>
    <RTDT>20171110</RTDT>
    <TKDT>20171111</TKDT>
  </F05CONTENT>
  <F05CONTENT>
    <BC1>248010990</BC1>
    <BC2>0000632330000098</BC2>
    <STNO>F011980</STNO>
    <RTDT>20171110</RTDT>
    <TKDT>20171111</TKDT>
  </F05CONTENT>
  <F05CONTENT>
    <BC1>248010990</BC1>
    <BC2>0000633230000017</BC2>
    <STNO>F007080</STNO>
    <RTDT>20171110</RTDT>
    <TKDT>20171111</TKDT>
  </F05CONTENT>
  <F05CONTENT>
    <BC1>248010990</BC1>
    <BC2>0000634330000008</BC2>
    <STNO>F009117</STNO>
    <RTDT>20171110</RTDT>
    <TKDT>20171111</TKDT>
  </F05CONTENT>
</F05DOC>