<?xml version="1.0" encoding="big5"?>
<F05DOC>
  <DOCHEAD>
    <DOCDATE>20170520</DOCDATE>
    <FROMPARTNERCODE>CVS</FROMPARTNERCODE>
    <TOPARTNERCODE>248</TOPARTNERCODE>
  </DOCHEAD>
  <F05CONTENT>
    <BC1>248700990</BC1>
    <BC2>0249310030000079</BC2>
    <STNO>F008637</STNO>
    <RTDT>20170519</RTDT>
    <TKDT>20170520</TKDT>
  </F05CONTENT>
  <F05CONTENT>
    <BC1>248700990</BC1>
    <BC2>0249320030000078</BC2>
    <STNO>K000879</STNO>
    <RTDT>20170519</RTDT>
    <TKDT>20170520</TKDT>
  </F05CONTENT>
  <F05CONTENT>
    <BC1>248700990</BC1>
    <BC2>0249600030000019</BC2>
    <STNO>F004497</STNO>
    <RTDT>20170519</RTDT>
    <TKDT>20170520</TKDT>
  </F05CONTENT>
  <F05CONTENT>
    <BC1>248700990</BC1>
    <BC2>0249910030000029</BC2>
    <STNO>F009805</STNO>
    <RTDT>20170519</RTDT>
    <TKDT>20170520</TKDT>
  </F05CONTENT>
  <F05CONTENT>
    <BC1>248700990</BC1>
    <BC2>0249930030000021</BC2>
    <STNO>F009805</STNO>
    <RTDT>20170519</RTDT>
    <TKDT>20170520</TKDT>
  </F05CONTENT>
  <F05CONTENT>
    <BC1>248700990</BC1>
    <BC2>0250530030000013</BC2>
    <STNO>F008879</STNO>
    <RTDT>20170519</RTDT>
    <TKDT>20170520</TKDT>
  </F05CONTENT>
  <F05CONTENT>
    <BC1>248700990</BC1>
    <BC2>0250670030000007</BC2>
    <STNO>F008500</STNO>
    <RTDT>20170519</RTDT>
    <TKDT>20170520</TKDT>
  </F05CONTENT>
  <F05CONTENT>
    <BC1>248700990</BC1>
    <BC2>0251040030000055</BC2>
    <STNO>F004210</STNO>
    <RTDT>20170519</RTDT>
    <TKDT>20170520</TKDT>
  </F05CONTENT>
</F05DOC>